<?xml version="1.0" encoding="UTF-8"?>
<mdb:MD_Metadata xmlns:mdb="http://standards.iso.org/19115/-3/mdb/1.0/2014-12-25"
	xmlns:mdq="http://standards.iso.org/19157/-2/mdq/1.0/2014-12-25"
	xmlns:mcc="http://standards.iso.org/19115/-3/mcc/1.0/2014-12-25"
	xmlns:gco="http://standards.iso.org/19139/gco/1.0/2014-12-25">
	<mdb:dataQualityInfo>
		<mdq:DQ_DataQuality>
			<mdq:scope>
				<mcc:MD_Scope>
					<mcc:level>
						<mcc:MD_ScopeCode codeList="http://standards.iso.org/ittf/PubliclyAvailableStandards/ISO_19139_Schemas/resources/codelist/ML_gmxCodelists.xml#MD_ScopeCode" codeListValue=""/>
					</mcc:level>
				</mcc:MD_Scope>
			</mdq:scope>
			<mdq:report>
				<mdq:DQ_DomainConsistency>
					<dqc:dateTime xmlns:dqc="http://standards.iso.org/19157/-2/dqc/1.0/2014-12-25">
						<gco:Date/>
					</dqc:dateTime>
					<mdq:result>
						<mdq:DQ_ConformanceResult>
						</mdq:DQ_ConformanceResult>
					</mdq:result>
				</mdq:DQ_DomainConsistency>
			</mdq:report>
		</mdq:DQ_DataQuality>
	</mdb:dataQualityInfo>
</mdb:MD_Metadata>

